src/rv32i.v
module rv32i (
    input wire clk_i,
    output wire [31:0] ibus_addr_o,
    input wire [31:0] ibus_data_i,
    output wire [3:0] dbus_en_o,
    output wire [31:0] dbus_write_addr_o,
    output wire [31:0] dbus_read_addr_o,
    output wire [31:0] dbus_write_data_o,
    input wire [31:0] dbus_read_data_i
);
    reg [31:0] pc = 0;
    reg [31:0] xreg [0:31]; integer i; initial for (i = 0; i < 32; i = i + 1) xreg[i] = 0;
    assign ibus_addr_o = pc;
    

    wire [31:0] insn = ibus_data_i;

    wire [6:0] opcode = insn[6:0];
    wire [4:0] rd = insn[11:7];
    wire [2:0] funct3 = insn[14:12];
    wire [4:0] rs1 = insn[19:15];
    wire [4:0] rs2 = insn[24:20];
    wire [6:0] funct7 = insn[31:25];

    wire [31:0] i_imm = {{20{insn[31]}}, insn[31:20]};
    wire [31:0] s_imm = {{20{insn[31]}}, insn[31:25], insn[11:7]};
    wire [31:0] b_imm = {{19{insn[31]}}, insn[31], insn[7], insn[30:25], insn[11:8], 1'b0};
    wire [31:0] u_imm = {insn[31:12], 12'b0};
    wire [31:0] j_imm = {{11{insn[31]}}, insn[31], insn[19:12], insn[20], insn[30:21], 1'b0};

    wire [31:0] branch_target = pc + b_imm;
    wire [31:0] jump_target = pc + j_imm;

    wire [31:0] dbus_read_data = dbus_read_data_i;
    assign dbus_en_o = dbus_en;
    assign dbus_write_addr_o = xreg[rs1] + s_imm;
    assign dbus_read_addr_o = xreg[rs1] + i_imm;
    assign dbus_write_data_o = dbus_write_data;

    always @(posedge clk_i) begin
        pc <= npc;
        if (xreg_en && rd != 0) xreg[rd] <= xreg_write_data;
    end

    reg [31:0] npc;
    reg xreg_en;
    reg [31:0] xreg_write_data;
    reg [3:0] dbus_en;
    reg [31:0] dbus_write_data;
    `include "riscv.vh"
    always @(*) begin
        npc = pc + 4;
        xreg_en = 0;
        xreg_write_data = 0;
        dbus_en = 0;
        dbus_write_data = 0;
        casez(insn)
            ADD      :begin xreg_en=1; xreg_write_data = xreg[rs1] + xreg[rs2]; end
            ADDI     :begin xreg_en=1; xreg_write_data = xreg[rs1] + i_imm; end
            AND      :begin xreg_en=1; xreg_write_data = xreg[rs1] & xreg[rs2]; end
            ANDI     :begin xreg_en=1; xreg_write_data = xreg[rs1] & i_imm; end
            AUIPC    :begin xreg_en=1; xreg_write_data = pc + u_imm; end
            BEQ      :begin if (xreg[rs1] == xreg[rs2]) npc = branch_target; end
            BGE      :begin if ($signed(xreg[rs1]) >= $signed(xreg[rs2])) npc = branch_target; end
            BGEU     :begin if (xreg[rs1] >= xreg[rs2]) npc = branch_target; end
            BLT      :begin if ($signed(xreg[rs1]) < $signed(xreg[rs2])) npc = branch_target; end
            BLTU     :begin if (xreg[rs1] < xreg[rs2]) npc = branch_target; end
            BNE      :begin if (xreg[rs1] != xreg[rs2]) npc = branch_target; end
            EBREAK   :begin $display("NOT SUPPORTED!"); end
            ECALL    :begin $display("NOT SUPPORTED!"); end
            FENCE    :begin $display("NOT SUPPORTED!"); end
            JAL      :begin xreg_en=1; xreg_write_data = pc+4; npc = jump_target; end
            JALR     :begin xreg_en=1; xreg_write_data = pc+4; npc = (xreg[rs1] + i_imm) & ~32'b1; end
            LB       :begin xreg_en=1; xreg_write_data = {{24{dbus_read_data[7]}}, dbus_read_data[7:0]}; end
            LBU      :begin xreg_en=1; xreg_write_data = dbus_read_data[7:0]; end
            LH       :begin xreg_en=1; xreg_write_data = {{16{dbus_read_data[15]}}, dbus_read_data[15:0]}; end
            LHU      :begin xreg_en=1; xreg_write_data = dbus_read_data[15:0]; end
            LUI      :begin xreg_en=1; xreg_write_data = u_imm; end
            LW       :begin xreg_en=1; xreg_write_data = dbus_read_data[31:0]; end
            OR       :begin xreg_en=1; xreg_write_data = xreg[rs1] | xreg[rs2]; end
            ORI      :begin xreg_en=1; xreg_write_data = xreg[rs1] | i_imm; end
            SB       :begin dbus_en=1; dbus_write_data = xreg[rs2][7:0]; end
            SH       :begin dbus_en=3; dbus_write_data = xreg[rs2][15:0]; end
            SLL      :begin xreg_en=1; xreg_write_data = xreg[rs1] << xreg[rs2][4:0]; end
            SLLI     :begin xreg_en=1; xreg_write_data = xreg[rs1] << i_imm[4:0]; end
            SLT      :begin xreg_en=1; xreg_write_data = ($signed(xreg[rs1]) < $signed(xreg[rs2])); end
            SLTI     :begin xreg_en=1; xreg_write_data = ($signed(xreg[rs1]) < $signed(i_imm)); end
            SLTIU    :begin xreg_en=1; xreg_write_data = (xreg[rs1] < i_imm); end
            SLTU     :begin xreg_en=1; xreg_write_data = (xreg[rs1] < xreg[rs2]); end
            SRA      :begin xreg_en=1; xreg_write_data = $signed(xreg[rs1]) >>> xreg[rs2][4:0]; end
            SRAI     :begin xreg_en=1; xreg_write_data = $signed(xreg[rs1]) >>> i_imm[4:0]; end
            SRL      :begin xreg_en=1; xreg_write_data = xreg[rs1] >> xreg[rs2][4:0]; end
            SRLI     :begin xreg_en=1; xreg_write_data = xreg[rs1] >> i_imm[4:0]; end
            SUB      :begin xreg_en=1; xreg_write_data = xreg[rs1] - xreg[rs2]; end
            SW       :begin dbus_en=15;dbus_write_data = xreg[rs2]; end
            XOR      :begin xreg_en=1; xreg_write_data = xreg[rs1] ^ xreg[rs2]; end
            XORI     :begin xreg_en=1; xreg_write_data = xreg[rs1] ^ i_imm; end
            default   :begin $display("Unknown instruction: %h", insn); end
        endcase
    end
endmodule

src/main.v
module main(
    input wire clk_i,
    input  wire rx_i,
    output wire tx_o
);
    reg [7:0] ram [0:4095]; // 4KB RAM
    wire [31:0] ibus_addr;
    wire [31:0] ibus_data = {ram[ibus_addr+3],
                             ram[ibus_addr+2],
                             ram[ibus_addr+1],
                             ram[ibus_addr+0]};
    wire [3:0]dbus_en;
    wire [31:0] dbus_read_addr;
    wire [31:0] dbus_write_addr;
    wire [31:0] dbus_write_data;
    always @(posedge clk_i) begin
        if (dbus_en[0]) ram[dbus_write_addr+0] <= dbus_write_data[7:0];
        if (dbus_en[1]) ram[dbus_write_addr+1] <= dbus_write_data[15:8];
        if (dbus_en[2]) ram[dbus_write_addr+2] <= dbus_write_data[23:16];
        if (dbus_en[3]) ram[dbus_write_addr+3] <= dbus_write_data[31:24];
    end

    wire [31:0] dbus_read_data = {ram[dbus_read_addr+3],
                                  ram[dbus_read_addr+2],
                                  ram[dbus_read_addr+1],
                                  ram[dbus_read_addr+0]};
    rv32i proc (
        .clk_i(clk_i),
        .ibus_addr_o(ibus_addr),
        .ibus_data_i(ibus_data),
        .dbus_en_o(dbus_en),
        .dbus_read_addr_o(dbus_read_addr),
        .dbus_write_addr_o(dbus_write_addr),
        .dbus_write_data_o(dbus_write_data),
        .dbus_read_data_i(dbus_read_data)
    );
    assign tx_o = 1'b1;
endmodule

src/top.v
module top;
    reg clk = 1; initial forever #5 clk = ~clk; // 100MHz clock
    reg [63:0] cc = 0; always @(posedge clk) cc <= cc+1; // clock cycle counter

    string hex_file;
    initial begin
        if ($value$plusargs("hex_file=%s", hex_file)) begin
            $display("Loading hex file: %s", hex_file);
            $readmemh(hex_file, top.dut.ram);
        end else begin
            $display("No hex file specified, using default values.");
        end
    end

    initial begin
        $dumpfile("top.vcd");
        $dumpvars(0, top);
    end

    reg done = 0;
    always @(posedge clk) begin
        if (top.dut.dbus_en == 4'b1111 && top.dut.dbus_write_addr == 32'h40008000) begin
            if (top.dut.dbus_write_data == 777) $finish;
            else $fatal;
        end
        else if (cc == 1000) $fatal;
    end

    main dut(
        .clk_i(clk),
        .rx_i(1'b1),
        .tx_o()
    );
endmodule

top.vcd
$version Generated by VerilatedVcd $end
$timescale 1ps $end
 $scope module TOP $end
  $scope module top $end
   $var wire 1 \ clk $end
   $var wire 64 D cc [63:0] $end
   $var wire 1 ^ done $end
   $scope module dut $end
    $var wire 1 \ clk_i $end
    $var wire 1 _ rx_i $end
    $var wire 1 _ tx_o $end
    $var wire 32 F ibus_addr [31:0] $end
    $var wire 32 G ibus_data [31:0] $end
    $var wire 4 H dbus_en [3:0] $end
    $var wire 32 I dbus_read_addr [31:0] $end
    $var wire 32 J dbus_write_addr [31:0] $end
    $var wire 32 K dbus_write_data [31:0] $end
    $var wire 32 # dbus_read_data [31:0] $end
    $scope module proc $end
     $var wire 1 \ clk_i $end
     $var wire 32 F ibus_addr_o [31:0] $end
     $var wire 32 G ibus_data_i [31:0] $end
     $var wire 4 H dbus_en_o [3:0] $end
     $var wire 32 J dbus_write_addr_o [31:0] $end
     $var wire 32 I dbus_read_addr_o [31:0] $end
     $var wire 32 K dbus_write_data_o [31:0] $end
     $var wire 32 # dbus_read_data_i [31:0] $end
     $var wire 32 F pc [31:0] $end
     $var wire 32 $ xreg[0] [31:0] $end
     $var wire 32 % xreg[1] [31:0] $end
     $var wire 32 & xreg[2] [31:0] $end
     $var wire 32 ' xreg[3] [31:0] $end
     $var wire 32 ( xreg[4] [31:0] $end
     $var wire 32 ) xreg[5] [31:0] $end
     $var wire 32 * xreg[6] [31:0] $end
     $var wire 32 + xreg[7] [31:0] $end
     $var wire 32 , xreg[8] [31:0] $end
     $var wire 32 - xreg[9] [31:0] $end
     $var wire 32 . xreg[10] [31:0] $end
     $var wire 32 / xreg[11] [31:0] $end
     $var wire 32 0 xreg[12] [31:0] $end
     $var wire 32 1 xreg[13] [31:0] $end
     $var wire 32 2 xreg[14] [31:0] $end
     $var wire 32 3 xreg[15] [31:0] $end
     $var wire 32 4 xreg[16] [31:0] $end
     $var wire 32 5 xreg[17] [31:0] $end
     $var wire 32 6 xreg[18] [31:0] $end
     $var wire 32 7 xreg[19] [31:0] $end
     $var wire 32 8 xreg[20] [31:0] $end
     $var wire 32 9 xreg[21] [31:0] $end
     $var wire 32 : xreg[22] [31:0] $end
     $var wire 32 ; xreg[23] [31:0] $end
     $var wire 32 < xreg[24] [31:0] $end
     $var wire 32 = xreg[25] [31:0] $end
     $var wire 32 > xreg[26] [31:0] $end
     $var wire 32 ? xreg[27] [31:0] $end
     $var wire 32 @ xreg[28] [31:0] $end
     $var wire 32 A xreg[29] [31:0] $end
     $var wire 32 B xreg[30] [31:0] $end
     $var wire 32 C xreg[31] [31:0] $end
     $var wire 32 ] i [31:0] $end
     $var wire 32 G insn [31:0] $end
     $var wire 7 L opcode [6:0] $end
     $var wire 5 M rd [4:0] $end
     $var wire 3 N funct3 [2:0] $end
     $var wire 5 O rs1 [4:0] $end
     $var wire 5 P rs2 [4:0] $end
     $var wire 7 Q funct7 [6:0] $end
     $var wire 32 R i_imm [31:0] $end
     $var wire 32 S s_imm [31:0] $end
     $var wire 32 T b_imm [31:0] $end
     $var wire 32 U u_imm [31:0] $end
     $var wire 32 V j_imm [31:0] $end
     $var wire 32 W branch_target [31:0] $end
     $var wire 32 X jump_target [31:0] $end
     $var wire 32 # dbus_read_data [31:0] $end
     $var wire 32 Y npc [31:0] $end
     $var wire 1 Z xreg_en $end
     $var wire 32 [ xreg_write_data [31:0] $end
     $var wire 4 H dbus_en [3:0] $end
     $var wire 32 K dbus_write_data [31:0] $end
     $var wire 32 ` ADD [31:0] $end
     $var wire 32 a ADDI [31:0] $end
     $var wire 32 b AND [31:0] $end
     $var wire 32 c ANDI [31:0] $end
     $var wire 32 d AUIPC [31:0] $end
     $var wire 32 e BEQ [31:0] $end
     $var wire 32 f BGE [31:0] $end
     $var wire 32 g BGEU [31:0] $end
     $var wire 32 h BLT [31:0] $end
     $var wire 32 i BLTU [31:0] $end
     $var wire 32 j BNE [31:0] $end
     $var wire 32 k EBREAK [31:0] $end
     $var wire 32 l ECALL [31:0] $end
     $var wire 32 m FENCE [31:0] $end
     $var wire 32 n JAL [31:0] $end
     $var wire 32 o JALR [31:0] $end
     $var wire 32 p LB [31:0] $end
     $var wire 32 q LBU [31:0] $end
     $var wire 32 r LH [31:0] $end
     $var wire 32 s LHU [31:0] $end
     $var wire 32 t LUI [31:0] $end
     $var wire 32 u LW [31:0] $end
     $var wire 32 v OR [31:0] $end
     $var wire 32 w ORI [31:0] $end
     $var wire 32 x SB [31:0] $end
     $var wire 32 y SH [31:0] $end
     $var wire 32 z SLL [31:0] $end
     $var wire 32 { SLLI [31:0] $end
     $var wire 32 | SLT [31:0] $end
     $var wire 32 } SLTI [31:0] $end
     $var wire 32 ~ SLTIU [31:0] $end
     $var wire 32 !! SLTU [31:0] $end
     $var wire 32 "! SRA [31:0] $end
     $var wire 32 #! SRAI [31:0] $end
     $var wire 32 $! SRL [31:0] $end
     $var wire 32 %! SRLI [31:0] $end
     $var wire 32 &! SUB [31:0] $end
     $var wire 32 '! SW [31:0] $end
     $var wire 32 (! XOR [31:0] $end
     $var wire 32 )! XORI [31:0] $end
    $upscope $end
   $upscope $end
  $upscope $end
 $upscope $end
$enddefinitions $end


#0
b00000000000000000000000010010011 #
b00000000000000000000000000000000 $
b00000000000000000000000000000000 %
b00000000000000000000000000000000 &
b00000000000000000000000000000000 '
b00000000000000000000000000000000 (
b00000000000000000000000000000000 )
b00000000000000000000000000000000 *
b00000000000000000000000000000000 +
b00000000000000000000000000000000 ,
b00000000000000000000000000000000 -
b00000000000000000000000000000000 .
b00000000000000000000000000000000 /
b00000000000000000000000000000000 0
b00000000000000000000000000000000 1
b00000000000000000000000000000000 2
b00000000000000000000000000000000 3
b00000000000000000000000000000000 4
b00000000000000000000000000000000 5
b00000000000000000000000000000000 6
b00000000000000000000000000000000 7
b00000000000000000000000000000000 8
b00000000000000000000000000000000 9
b00000000000000000000000000000000 :
b00000000000000000000000000000000 ;
b00000000000000000000000000000000 <
b00000000000000000000000000000000 =
b00000000000000000000000000000000 >
b00000000000000000000000000000000 ?
b00000000000000000000000000000000 @
b00000000000000000000000000000000 A
b00000000000000000000000000000000 B
b00000000000000000000000000000000 C
b0000000000000000000000000000000000000000000000000000000000000000 D
b00000000000000000000000000000000 F
b00000000000000000000000010010011 G
b0000 H
b00000000000000000000000000000000 I
b00000000000000000000000000000001 J
b00000000000000000000000000000000 K
b0010011 L
b00001 M
b000 N
b00000 O
b00000 P
b0000000 Q
b00000000000000000000000000000000 R
b00000000000000000000000000000001 S
b00000000000000000000100000000000 T
b00000000000000000000000000000000 U
b00000000000000000000000000000000 V
b00000000000000000000100000000000 W
b00000000000000000000000000000000 X
b00000000000000000000000000000100 Y
1Z
b00000000000000000000000000000000 [
1\
b00000000000000000000000000100000 ]
0^
1_
b00000000000000000000000000110011 `
b00000000000000000000000000010011 a
b00000000000000000111000000110011 b
b00000000000000000111000000010011 c
b00000000000000000000000000010111 d
b00000000000000000000000001100011 e
b00000000000000000101000001100011 f
b00000000000000000111000001100011 g
b00000000000000000100000001100011 h
b00000000000000000110000001100011 i
b00000000000000000001000001100011 j
b00000000000100000000000001110011 k
b00000000000000000000000001110011 l
b00000000000000000000000000001111 m
b00000000000000000000000001101111 n
b00000000000000000000000001100111 o
b00000000000000000000000000000011 p
b00000000000000000100000000000011 q
b00000000000000000001000000000011 r
b00000000000000000101000000000011 s
b00000000000000000000000000110111 t
b00000000000000000010000000000011 u
b00000000000000000110000000110011 v
b00000000000000000110000000010011 w
b00000000000000000000000000100011 x
b00000000000000000001000000100011 y
b00000000000000000001000000110011 z
b00000000000000000001000000010011 {
b00000000000000000010000000110011 |
b00000000000000000010000000010011 }
b00000000000000000011000000010011 ~
b00000000000000000011000000110011 !!
b01000000000000000101000000110011 "!
b01000000000000000101000000010011 #!
b00000000000000000101000000110011 $!
b00000000000000000101000000010011 %!
b01000000000000000000000000110011 &!
b00000000000000000010000000100011 '!
b00000000000000000100000000110011 (!
b00000000000000000100000000010011 )!
#5
0\
#10
b0000000000000000000000000000000000000000000000000000000000000001 D
b00000000000000000000000000000100 F
b00000000000000000000000100010011 G
b00000000000000000000000000000010 J
b00010 M
b00000000000000000000000000000010 S
b00000000000000000000000000000010 T
b00000000000000000000000000000110 W
b00000000000000000000000000000100 X
b00000000000000000000000000001000 Y
1\
#15
0\
#20
b0000000000000000000000000000000000000000000000000000000000000010 D
b00000000000000000000000000001000 F
b00000000000000000000000110010011 G
b00000000000000000000000000000011 J
b00011 M
b00000000000000000000000000000011 S
b00000000000000000000100000000010 T
b00000000000000000000100000001010 W
b00000000000000000000000000001000 X
b00000000000000000000000000001100 Y
1\
#25
0\
#30
b0000000000000000000000000000000000000000000000000000000000000011 D
b00000000000000000000000000001100 F
b00000000000000000000001000010011 G
b00000000000000000000000000000100 J
b00100 M
b00000000000000000000000000000100 S
b00000000000000000000000000000100 T
b00000000000000000000000000010000 W
b00000000000000000000000000001100 X
b00000000000000000000000000010000 Y
1\
#35
0\
#40
b0000000000000000000000000000000000000000000000000000000000000100 D
b00000000000000000000000000010000 F
b00000000000000000000001010010011 G
b00000000000000000000000000000101 J
b00101 M
b00000000000000000000000000000101 S
b00000000000000000000100000000100 T
b00000000000000000000100000010100 W
b00000000000000000000000000010000 X
b00000000000000000000000000010100 Y
1\
#45
0\
#50
b0000000000000000000000000000000000000000000000000000000000000101 D
b00000000000000000000000000010100 F
b00000000000000000000001100010011 G
b00000000000000000000000000000110 J
b00110 M
b00000000000000000000000000000110 S
b00000000000000000000000000000110 T
b00000000000000000000000000011010 W
b00000000000000000000000000010100 X
b00000000000000000000000000011000 Y
1\
#55
0\
#60
b0000000000000000000000000000000000000000000000000000000000000110 D
b00000000000000000000000000011000 F
b00000000000000000000001110010011 G
b00000000000000000000000000000111 J
b00111 M
b00000000000000000000000000000111 S
b00000000000000000000100000000110 T
b00000000000000000000100000011110 W
b00000000000000000000000000011000 X
b00000000000000000000000000011100 Y
1\
#65
0\
#70
b0000000000000000000000000000000000000000000000000000000000000111 D
b00000000000000000000000000011100 F
b00000000000000000000010000010011 G
b00000000000000000000000000001000 J
b01000 M
b00000000000000000000000000001000 S
b00000000000000000000000000001000 T
b00000000000000000000000000100100 W
b00000000000000000000000000011100 X
b00000000000000000000000000100000 Y
1\
#75
0\
#80
b0000000000000000000000000000000000000000000000000000000000001000 D
b00000000000000000000000000100000 F
b00000000000000000000010010010011 G
b00000000000000000000000000001001 J
b01001 M
b00000000000000000000000000001001 S
b00000000000000000000100000001000 T
b00000000000000000000100000101000 W
b00000000000000000000000000100000 X
b00000000000000000000000000100100 Y
1\
#85
0\
#90
b0000000000000000000000000000000000000000000000000000000000001001 D
b00000000000000000000000000100100 F
b00000000000000000000010100010011 G
b00000000000000000000000000001010 J
b01010 M
b00000000000000000000000000001010 S
b00000000000000000000000000001010 T
b00000000000000000000000000101110 W
b00000000000000000000000000100100 X
b00000000000000000000000000101000 Y
1\
#95
0\
#100
b0000000000000000000000000000000000000000000000000000000000001010 D
b00000000000000000000000000101000 F
b00000000000000000000010110010011 G
b00000000000000000000000000001011 J
b01011 M
b00000000000000000000000000001011 S
b00000000000000000000100000001010 T
b00000000000000000000100000110010 W
b00000000000000000000000000101000 X
b00000000000000000000000000101100 Y
1\
#105
0\
#110
b0000000000000000000000000000000000000000000000000000000000001011 D
b00000000000000000000000000101100 F
b00000000000000000000011000010011 G
b00000000000000000000000000001100 J
b01100 M
b00000000000000000000000000001100 S
b00000000000000000000000000001100 T
b00000000000000000000000000111000 W
b00000000000000000000000000101100 X
b00000000000000000000000000110000 Y
1\
#115
0\
#120
b0000000000000000000000000000000000000000000000000000000000001100 D
b00000000000000000000000000110000 F
b00000000000000000000011010010011 G
b00000000000000000000000000001101 J
b01101 M
b00000000000000000000000000001101 S
b00000000000000000000100000001100 T
b00000000000000000000100000111100 W
b00000000000000000000000000110000 X
b00000000000000000000000000110100 Y
1\
#125
0\
#130
b0000000000000000000000000000000000000000000000000000000000001101 D
b00000000000000000000000000110100 F
b00000000000000000000011100010011 G
b00000000000000000000000000001110 J
b01110 M
b00000000000000000000000000001110 S
b00000000000000000000000000001110 T
b00000000000000000000000001000010 W
b00000000000000000000000000110100 X
b00000000000000000000000000111000 Y
1\
#135
0\
#140
b0000000000000000000000000000000000000000000000000000000000001110 D
b00000000000000000000000000111000 F
b00000000000000000000011110010011 G
b00000000000000000000000000001111 J
b01111 M
b00000000000000000000000000001111 S
b00000000000000000000100000001110 T
b00000000000000000000100001000110 W
b00000000000000000000000000111000 X
b00000000000000000000000000111100 Y
1\
#145
0\
#150
b0000000000000000000000000000000000000000000000000000000000001111 D
b00000000000000000000000000111100 F
b00000000000000000000100000010011 G
b00000000000000000000000000010000 J
b10000 M
b00000000000000000000000000010000 S
b00000000000000000000000000010000 T
b00000000000000000000000001001100 W
b00000000000000000000000000111100 X
b00000000000000000000000001000000 Y
1\
#155
0\
#160
b0000000000000000000000000000000000000000000000000000000000010000 D
b00000000000000000000000001000000 F
b00000000000000000000100010010011 G
b00000000000000000000000000010001 J
b10001 M
b00000000000000000000000000010001 S
b00000000000000000000100000010000 T
b00000000000000000000100001010000 W
b00000000000000000000000001000000 X
b00000000000000000000000001000100 Y
1\
#165
0\
#170
b0000000000000000000000000000000000000000000000000000000000010001 D
b00000000000000000000000001000100 F
b00000000000000000000100100010011 G
b00000000000000000000000000010010 J
b10010 M
b00000000000000000000000000010010 S
b00000000000000000000000000010010 T
b00000000000000000000000001010110 W
b00000000000000000000000001000100 X
b00000000000000000000000001001000 Y
1\
#175
0\
#180
b0000000000000000000000000000000000000000000000000000000000010010 D
b00000000000000000000000001001000 F
b00000000000000000000100110010011 G
b00000000000000000000000000010011 J
b10011 M
b00000000000000000000000000010011 S
b00000000000000000000100000010010 T
b00000000000000000000100001011010 W
b00000000000000000000000001001000 X
b00000000000000000000000001001100 Y
1\
#185
0\
#190
b0000000000000000000000000000000000000000000000000000000000010011 D
b00000000000000000000000001001100 F
b00000000000000000000101000010011 G
b00000000000000000000000000010100 J
b10100 M
b00000000000000000000000000010100 S
b00000000000000000000000000010100 T
b00000000000000000000000001100000 W
b00000000000000000000000001001100 X
b00000000000000000000000001010000 Y
1\
#195
0\
#200
b0000000000000000000000000000000000000000000000000000000000010100 D
b00000000000000000000000001010000 F
b00000000000000000000101010010011 G
b00000000000000000000000000010101 J
b10101 M
b00000000000000000000000000010101 S
b00000000000000000000100000010100 T
b00000000000000000000100001100100 W
b00000000000000000000000001010000 X
b00000000000000000000000001010100 Y
1\
#205
0\
#210
b0000000000000000000000000000000000000000000000000000000000010101 D
b00000000000000000000000001010100 F
b00000000000000000000101100010011 G
b00000000000000000000000000010110 J
b10110 M
b00000000000000000000000000010110 S
b00000000000000000000000000010110 T
b00000000000000000000000001101010 W
b00000000000000000000000001010100 X
b00000000000000000000000001011000 Y
1\
#215
0\
#220
b0000000000000000000000000000000000000000000000000000000000010110 D
b00000000000000000000000001011000 F
b00000000000000000000101110010011 G
b00000000000000000000000000010111 J
b10111 M
b00000000000000000000000000010111 S
b00000000000000000000100000010110 T
b00000000000000000000100001101110 W
b00000000000000000000000001011000 X
b00000000000000000000000001011100 Y
1\
#225
0\
#230
b0000000000000000000000000000000000000000000000000000000000010111 D
b00000000000000000000000001011100 F
b00000000000000000000110000010011 G
b00000000000000000000000000011000 J
b11000 M
b00000000000000000000000000011000 S
b00000000000000000000000000011000 T
b00000000000000000000000001110100 W
b00000000000000000000000001011100 X
b00000000000000000000000001100000 Y
1\
#235
0\
#240
b0000000000000000000000000000000000000000000000000000000000011000 D
b00000000000000000000000001100000 F
b00000000000000000000110010010011 G
b00000000000000000000000000011001 J
b11001 M
b00000000000000000000000000011001 S
b00000000000000000000100000011000 T
b00000000000000000000100001111000 W
b00000000000000000000000001100000 X
b00000000000000000000000001100100 Y
1\
#245
0\
#250
b0000000000000000000000000000000000000000000000000000000000011001 D
b00000000000000000000000001100100 F
b00000000000000000000110100010011 G
b00000000000000000000000000011010 J
b11010 M
b00000000000000000000000000011010 S
b00000000000000000000000000011010 T
b00000000000000000000000001111110 W
b00000000000000000000000001100100 X
b00000000000000000000000001101000 Y
1\
#255
0\
#260
b0000000000000000000000000000000000000000000000000000000000011010 D
b00000000000000000000000001101000 F
b00000000000000000000110110010011 G
b00000000000000000000000000011011 J
b11011 M
b00000000000000000000000000011011 S
b00000000000000000000100000011010 T
b00000000000000000000100010000010 W
b00000000000000000000000001101000 X
b00000000000000000000000001101100 Y
1\
#265
0\
#270
b0000000000000000000000000000000000000000000000000000000000011011 D
b00000000000000000000000001101100 F
b00000000000000000000111000010011 G
b00000000000000000000000000011100 J
b11100 M
b00000000000000000000000000011100 S
b00000000000000000000000000011100 T
b00000000000000000000000010001000 W
b00000000000000000000000001101100 X
b00000000000000000000000001110000 Y
1\
#275
0\
#280
b0000000000000000000000000000000000000000000000000000000000011100 D
b00000000000000000000000001110000 F
b00000000000000000000111010010011 G
b00000000000000000000000000011101 J
b11101 M
b00000000000000000000000000011101 S
b00000000000000000000100000011100 T
b00000000000000000000100010001100 W
b00000000000000000000000001110000 X
b00000000000000000000000001110100 Y
1\
#285
0\
#290
b0000000000000000000000000000000000000000000000000000000000011101 D
b00000000000000000000000001110100 F
b00000000000000000000111100010011 G
b00000000000000000000000000011110 J
b11110 M
b00000000000000000000000000011110 S
b00000000000000000000000000011110 T
b00000000000000000000000010010010 W
b00000000000000000000000001110100 X
b00000000000000000000000001111000 Y
1\
#295
0\
#300
b0000000000000000000000000000000000000000000000000000000000011110 D
b00000000000000000000000001111000 F
b00000000000000000000111110010011 G
b00000000000000000000000000011111 J
b11111 M
b00000000000000000000000000011111 S
b00000000000000000000100000011110 T
b00000000000000000000100010010110 W
b00000000000000000000000001111000 X
b00000000000000000000000001111100 Y
1\
#305
0\
#310
b00000001000100110000000000000000 #
b0000000000000000000000000000000000000000000000000000000000011111 D
b00000000000000000000000001111100 F
b00000000001000000000000110010011 G
b00000000000000000000000000000010 I
b00000000000000000000000000000011 J
b00011 M
b00010 P
b00000000000000000000000000000010 R
b00000000000000000000000000000011 S
b00000000000000000000100000000010 T
b00000000001000000000000000000000 U
b00000000000000000000000000000010 V
b00000000000000000000100001111110 W
b00000000000000000000000001111110 X
b00000000000000000000000010000000 Y
b00000000000000000000000000000010 [
1\
#315
0\
#320
b00000000000000101001001100000000 #
b00000000000000000000000000000010 '
b0000000000000000000000000000000000000000000000000000000000100000 D
b00000000000000000000000010000000 F
b00000000111111110001011010110111 G
b00000000000000000000000000001111 I
b00000000000000000000000000001101 J
b0110111 L
b01101 M
b001 N
b11110 O
b01111 P
b00000000000000000000000000001111 R
b00000000000000000000000000001101 S
b00000000000000000000100000001100 T
b00000000111111110001000000000000 U
b00000000000011110001100000001110 V
b00000000000000000000100010001100 W
b00000000000011110001100010001110 X
b00000000000000000000000010000100 Y
b00000000111111110001000000000000 [
1\
#325
0\
#330
b00000000000000000000000000000000 #
b00000000111111110001000000000000 1
b0000000000000000000000000000000000000000000000000000000000100001 D
b00000000000000000000000010000100 F
b11110000000001101000011010010011 G
b00000000111111110000111100000000 I
b00000000111111110000111100001101 J
b0010011 L
b000 N
b01101 O
b00000 P
b1111000 Q
b11111111111111111111111100000000 R
b11111111111111111111111100001101 S
b11111111111111111111111100001100 T
b11110000000001101000000000000000 U
b11111111111101101000011100000000 V
b11111111111111111111111110010000 W
b11111111111101101000011110000100 X
b00000000000000000000000010001000 Y
b00000000111111110000111100000000 [
1\
#335
0\
#340
b00000000111111110000111100000000 1
b0000000000000000000000000000000000000000000000000000000000100010 D
b00000000000000000000000010001000 F
b11110000111101101100011100010011 G
b00000000111111110000111000001111 I
b00000000111111110000111000001110 J
b01110 M
b100 N
b01111 P
b11111111111111111111111100001111 R
b11111111111111111111111100001110 S
b11111111111111111111011100001110 T
b11110000111101101100000000000000 U
b11111111111101101100111100001110 V
b11111111111111111111011110010110 W
b11111111111101101100111110010110 X
b00000000000000000000000010001100 Y
b11111111000000001111000000001111 [
1\
#345
0\
#350
b11111111000000001111000000001111 2
b0000000000000000000000000000000000000000000000000000000000100011 D
b00000000000000000000000010001100 F
b11111111000000001111001110110111 G
b11111111111111111111111111110000 I
b11111111111111111111111111100111 J
b0110111 L
b00111 M
b111 N
b00001 O
b10000 P
b1111111 Q
b11111111111111111111111111110000 R
b11111111111111111111111111100111 S
b11111111111111111111111111100110 T
b11111111000000001111000000000000 U
b11111111111100001111011111110000 V
b00000000000000000000000001110010 W
b11111111111100001111100001111100 X
b00000000000000000000000010010000 Y
b11111111000000001111000000000000 [
1\
#355
0\
#360
b00000000000000101001001100000000 #
b11111111000000001111000000000000 +
b0000000000000000000000000000000000000000000000000000000000100100 D
b00000000000000000000000010010000 F
b00000000111100111000001110010011 G
b11111111000000001111000000001111 I
b11111111000000001111000000000111 J
b0010011 L
b000 N
b00111 O
b01111 P
b0000000 Q
b00000000000000000000000000001111 R
b00000000000000000000000000000111 S
b00000000000000000000100000000110 T
b00000000111100111000000000000000 U
b00000000000000111000100000001110 V
b00000000000000000000100010010110 W
b00000000000000111000100010011110 X
b00000000000000000000000010010100 Y
b11111111000000001111000000001111 [
1\
#365
0\
#370
b00010000101101110000000000000000 #
b11111111000000001111000000001111 +
b0000000000000000000000000000000000000000000000000000000000100101 D
b00000000000000000000000010010100 F
b00011100011101110001011001100011 G
b11111111000000001111000111010110 I
b11111111000000001111000111011011 J
b1100011 L
b01100 M
b001 N
b01110 O
b00111 P
b0001110 Q
b00000000000000000000000111000111 R
b00000000000000000000000111001100 S
b00000000000000000000000111001100 T
b00011100011101110001000000000000 U
b00000000000001110001100111000110 V
b00000000000000000000001001100000 W
b00000000000001110001101001011010 X
b00000000000000000000000010011000 Y
0Z
b00000000000000000000000000000000 [
1\
#375
0\
